substream
