Metadata-Version: 2.1
Name: substream
Version: 0.1.1
Summary: Transcribes audio files to .srt
Home-page: UNKNOWN
Author: Michael de Gans
License: UNKNOWN
Project-URL: Bug Reports, https://github.com/mdegans/substream/issues
Project-URL: Source, https://github.com/mdegans/substream/
Platform: UNKNOWN
Classifier: Development Status :: 3 - Alpha
Classifier: Intended Audience :: End Users/Desktop
Classifier: Intended Audience :: Developers
Classifier: Topic :: Multimedia :: Sound/Audio :: Speech
Classifier: Topic :: Multimedia :: Sound/Audio :: Analysis
Classifier: Topic :: Text Processing :: Linguistic
Classifier: Topic :: Software Development :: Internationalization
Classifier: License :: OSI Approved :: MIT License
Classifier: Programming Language :: Python :: 3
Classifier: Programming Language :: Python :: 3.6
Classifier: Programming Language :: Python :: 3.7
Classifier: Programming Language :: Python :: 3.8
Requires-Python: >=3.6
